astrafocus/__init__.py
astrafocus/autofocuser.py
astrafocus/extremum_estimators.py
astrafocus/focus_measure_operators.py
astrafocus/star_finder.py
astrafocus/star_fitter.py
astrafocus/star_size_focus_measure_operators.py
astrafocus/interface/__init__.py
astrafocus/interface/alpaca_devices.py
astrafocus/interface/camera.py
astrafocus/interface/device_manager.py
astrafocus/interface/focuser.py
astrafocus/interface/simulation.py
astrafocus/interface/telescope.py
astrafocus/interface/telescope_specs.py
astrafocus/models/__init__.py
astrafocus/models/elliptical_moffat_2D.py
astrafocus/models/half_flux_radius_2D.py
astrafocus/sql/__init__.py
astrafocus/sql/local_gaia_database_query.py
astrafocus/sql/shardwise_query.py
astrafocus/targeting/__init__.py
astrafocus/targeting/airmass_models.py
astrafocus/targeting/angle_difference.py
astrafocus/targeting/celestial_bounds_calculator.py
astrafocus/targeting/tangential_plane_projector.py
astrafocus/targeting/zenith_angle_calculator.py
astrafocus/targeting/zenith_neighbourhood.py
astrafocus/targeting/zenith_neighbourhood_query.py
astrafocus/targeting/zenith_neighbourhood_query_result.py
astrafocus/utils/__init__.py
astrafocus/utils/fits.py
astrafocus/utils/logger.py
astrafocus/utils/plot.py
astrafocus/utils/timer.py
astrafocus/utils/typing.py
astrafocus-0.1.1.dist-info/licenses/LICENSE
astrafocus-0.1.1.dist-info/METADATA
astrafocus-0.1.1.dist-info/WHEEL
astrafocus-0.1.1.dist-info/top_level.txt
astrafocus-0.1.1.dist-info/RECORD
