Metadata-Version: 2.4
Name: astrafocus
Version: 0.1.1
Summary: My package description
Author-email: David Degen <ddegen@ethz.ch>
License: MIT
Project-URL: Bug Tracker, https://github.com/dgegen/astrafocus/issues
Project-URL: Homepage, https://github.com/dgegen/astrafocus
Project-URL: Source, https://github.com/dgegen/astrafocus
Keywords: telescope,autofocus
Classifier: Programming Language :: Python :: 3
Classifier: Programming Language :: Python :: 3.11
Classifier: Operating System :: OS Independent
Classifier: Intended Audience :: Developers
Requires-Python: >=3.11
License-File: LICENSE
Requires-Dist: astropy
Requires-Dist: opencv-python
Requires-Dist: numpy
Requires-Dist: pandas
Requires-Dist: photutils
Requires-Dist: scipy
Requires-Dist: sqlite3worker
Requires-Dist: statsmodels
Provides-Extra: alpaca
Requires-Dist: alpyca; extra == "alpaca"
Provides-Extra: dash
Requires-Dist: dash; extra == "dash"
Requires-Dist: dash_bootstrap_components; extra == "dash"
Requires-Dist: plotly; extra == "dash"
Provides-Extra: dev
Requires-Dist: cabaret; extra == "dev"
Requires-Dist: matplotlib; extra == "dev"
Requires-Dist: ruff; extra == "dev"
Requires-Dist: pytest; extra == "dev"
Provides-Extra: docs
Requires-Dist: sphinx; extra == "docs"
Requires-Dist: sphinx-book-theme; extra == "docs"
Requires-Dist: sphinx-design; extra == "docs"
Requires-Dist: sphinx-copybutton; extra == "docs"
Requires-Dist: ipython; extra == "docs"
Requires-Dist: matplotlib; extra == "docs"
Requires-Dist: notebook; extra == "docs"
Requires-Dist: ipywidgets; extra == "docs"
Requires-Dist: myst_nb; extra == "docs"
Requires-Dist: ghp-import; extra == "docs"
Requires-Dist: alpyca; extra == "docs"
Provides-Extra: extended
Requires-Dist: scikit-learn; extra == "extended"
Provides-Extra: test
Requires-Dist: pytest; extra == "test"
Requires-Dist: cabaret; extra == "test"
Provides-Extra: visualization
Requires-Dist: ipython; extra == "visualization"
Requires-Dist: matplotlib; extra == "visualization"
Requires-Dist: notebook; extra == "visualization"
Dynamic: license-file
